multifactor/__init__.py
multifactor/admin.py
multifactor/app_settings.py
multifactor/apps.py
multifactor/common.py
multifactor/decorators.py
multifactor/factors/__init__.py
multifactor/factors/fallback.py
multifactor/factors/fido2.py
multifactor/factors/totp.py
multifactor/migrations/0001_initial.py
multifactor/migrations/0002_auto_20190823_2128.py
multifactor/migrations/0003_userkey_name.py
multifactor/migrations/0004_alter_userkey_key_type.py
multifactor/migrations/__init__.py
multifactor/mixins.py
multifactor/models.py
multifactor/static/multifactor/js/multifactor.js
multifactor/static/multifactor/js/qrcode.js
multifactor/static/multifactor/js/qrcode.min.js
multifactor/static/multifactor/js/webauthn-json.browser-ponyfill.js
multifactor/static/multifactor/keys.svg
multifactor/static/multifactor/multifactor.css
multifactor/static/multifactor/multifactor.js
multifactor/templates/multifactor/FIDO2/add.html
multifactor/templates/multifactor/FIDO2/check.html
multifactor/templates/multifactor/TOTP/add.html
multifactor/templates/multifactor/TOTP/check.html
multifactor/templates/multifactor/add.html
multifactor/templates/multifactor/authenticate.html
multifactor/templates/multifactor/base.html
multifactor/templates/multifactor/brand.html
multifactor/templates/multifactor/fallback/auth.html
multifactor/templates/multifactor/fallback/email.html
multifactor/templates/multifactor/help.html
multifactor/templates/multifactor/home.html
multifactor/templates/multifactor/userkey_form.html
multifactor/urls.py
multifactor/views.py
django_multifactor-0.8.4.dist-info/LICENSE
django_multifactor-0.8.4.dist-info/METADATA
django_multifactor-0.8.4.dist-info/WHEEL
django_multifactor-0.8.4.dist-info/RECORD
