Metadata-Version: 2.3
Name: django-multifactor
Version: 0.8.4
Summary: Drop-in multifactor authentication subsystem for Django.
License: MIT
Author: Oli Warner
Author-email: oli@thepcspy.com
Requires-Python: >=3.8,<4.0
Classifier: Development Status :: 4 - Beta
Classifier: Environment :: Web Environment
Classifier: Framework :: Django
Classifier: Framework :: Django :: 2.2
Classifier: Framework :: Django :: 3.0
Classifier: Framework :: Django :: 3.1
Classifier: Framework :: Django :: 3.2
Classifier: Framework :: Django :: 4.0
Classifier: Framework :: Django :: 4.1
Classifier: Framework :: Django :: 4.2
Classifier: Framework :: Django :: 5.0
Classifier: Framework :: Django :: 5.1
Classifier: Framework :: Django :: 5.2
Classifier: Intended Audience :: Developers
Classifier: License :: OSI Approved :: MIT License
Classifier: Operating System :: OS Independent
Classifier: Programming Language :: Python
Classifier: Programming Language :: Python :: 3
Classifier: Programming Language :: Python :: 3.8
Classifier: Programming Language :: Python :: 3.9
Classifier: Programming Language :: Python :: 3.10
Classifier: Programming Language :: Python :: 3.11
Classifier: Programming Language :: Python :: 3.12
Classifier: Programming Language :: Python :: 3.13
Classifier: Topic :: Software Development :: Libraries :: Python Modules
Requires-Dist: Django (>2.2,<6) ; python_version < "3.10"
Requires-Dist: Django (>=4.2,<6) ; python_version >= "3.10"
Requires-Dist: fido2 (>=1.2.0,<1.3) ; python_version < "3.10"
Requires-Dist: fido2 (>=2.0.0) ; python_version >= "3.10"
Requires-Dist: pyotp (>=2.9,<3.0)
Project-URL: Homepage, https://github.com/oliwarner/django-multifactor
Project-URL: Repository, https://github.com/oliwarner/django-multifactor
